alibabacloud_accountcenter20241209/__init__.py
alibabacloud_accountcenter20241209/client.py
alibabacloud_accountcenter20241209/models/__init__.py
alibabacloud_accountcenter20241209/models/_account_contact_add_request.py
alibabacloud_accountcenter20241209/models/_account_contact_add_response.py
alibabacloud_accountcenter20241209/models/_account_contact_add_response_body.py
alibabacloud_accountcenter20241209/models/_account_contact_delete_request.py
alibabacloud_accountcenter20241209/models/_account_contact_delete_response.py
alibabacloud_accountcenter20241209/models/_account_contact_delete_response_body.py
alibabacloud_accountcenter20241209/models/_account_contact_edit_request.py
alibabacloud_accountcenter20241209/models/_account_contact_edit_response.py
alibabacloud_accountcenter20241209/models/_account_contact_edit_response_body.py
alibabacloud_accountcenter20241209/models/_account_contact_query_detail_request.py
alibabacloud_accountcenter20241209/models/_account_contact_query_detail_response.py
alibabacloud_accountcenter20241209/models/_account_contact_query_detail_response_body.py
alibabacloud_accountcenter20241209/models/_account_contact_query_page_list_request.py
alibabacloud_accountcenter20241209/models/_account_contact_query_page_list_response.py
alibabacloud_accountcenter20241209/models/_account_contact_query_page_list_response_body.py
alibabacloud_accountcenter20241209/models/_enterprise_account_change_login_password_request.py
alibabacloud_accountcenter20241209/models/_enterprise_account_change_login_password_response.py
alibabacloud_accountcenter20241209/models/_enterprise_account_change_login_password_response_body.py
alibabacloud_accountcenter20241209/models/_enterprise_account_change_security_email_request.py
alibabacloud_accountcenter20241209/models/_enterprise_account_change_security_email_response.py
alibabacloud_accountcenter20241209/models/_enterprise_account_change_security_email_response_body.py
alibabacloud_accountcenter20241209-1.2.0.dist-info/LICENSE
alibabacloud_accountcenter20241209-1.2.0.dist-info/METADATA
alibabacloud_accountcenter20241209-1.2.0.dist-info/WHEEL
alibabacloud_accountcenter20241209-1.2.0.dist-info/top_level.txt
alibabacloud_accountcenter20241209-1.2.0.dist-info/RECORD
